batdetect2/__init__.py
batdetect2/api.py
batdetect2/cli.py
batdetect2/plot.py
batdetect2/types.py
batdetect2/detector/__init__.py
batdetect2/detector/compute_features.py
batdetect2/detector/model_helpers.py
batdetect2/detector/models.py
batdetect2/detector/parameters.py
batdetect2/detector/post_process.py
batdetect2/evaluate/__init__.py
batdetect2/evaluate/evaluate_models.py
batdetect2/evaluate/readme.md
batdetect2/finetune/__init__.py
batdetect2/finetune/finetune_model.py
batdetect2/finetune/prep_data_finetune.py
batdetect2/finetune/readme.md
batdetect2/models/Net2DFast_UK_same.pth.tar
batdetect2/models/readme.md
batdetect2/train/__init__.py
batdetect2/train/audio_dataloader.py
batdetect2/train/evaluate.py
batdetect2/train/losses.py
batdetect2/train/readme.md
batdetect2/train/train_model.py
batdetect2/train/train_split.py
batdetect2/train/train_utils.py
batdetect2/utils/__init__.py
batdetect2/utils/audio_utils.py
batdetect2/utils/detector_utils.py
batdetect2/utils/plot_utils.py
batdetect2/utils/visualize.py
batdetect2/utils/wavfile.py
batdetect2-1.3.0.dist-info/METADATA
batdetect2-1.3.0.dist-info/WHEEL
batdetect2-1.3.0.dist-info/entry_points.txt
batdetect2-1.3.0.dist-info/licenses/LICENSE.md
batdetect2-1.3.0.dist-info/RECORD
