Metadata-Version: 2.4
Name: batdetect2
Version: 1.3.0
Summary: Deep learning model for detecting and classifying bat echolocation calls in high frequency audio recordings.
Author-email: Oisin Mac Aodha <oisin.macaodha@ed.ac.uk>, Santiago Martinez Balvanera <santiago.balvanera.20@ucl.ac.uk>
License: CC-by-nc-4
License-File: LICENSE.md
Keywords: audio,bat,classification,deep learning,detection,echolocation,machine learning
Classifier: Development Status :: 4 - Beta
Classifier: Intended Audience :: Science/Research
Classifier: Natural Language :: English
Classifier: Operating System :: OS Independent
Classifier: Programming Language :: Python :: 3.9
Classifier: Programming Language :: Python :: 3.10
Classifier: Programming Language :: Python :: 3.11
Classifier: Programming Language :: Python :: 3.12
Classifier: Topic :: Multimedia :: Sound/Audio :: Analysis
Classifier: Topic :: Scientific/Engineering :: Artificial Intelligence
Classifier: Topic :: Software Development :: Libraries :: Python Modules
Requires-Python: <3.13,>=3.9
Requires-Dist: click>=8.1.7
Requires-Dist: librosa>=0.10.1
Requires-Dist: matplotlib>=3.7.1
Requires-Dist: numpy>=1.23.5
Requires-Dist: pandas>=1.5.3
Requires-Dist: scikit-learn>=1.2.2
Requires-Dist: scipy>=1.10.1
Requires-Dist: torch<2.5.0,>=1.13.1
Requires-Dist: torchaudio<2.5.0,>=1.13.1
Requires-Dist: torchvision>=0.14.0
